{
	"name": "SDrop",
	"plugin-id": "Sprite",
	"sid": 382175733286746,
	"isGlobal": false,
	"instanceVariables": [
		{
			"name": "drop_uid",
			"type": "number",
			"desc": "",
			"sid": 796971647765676
		},
		{
			"name": "drop_type",
			"type": "number",
			"desc": "",
			"sid": 452896447245194
		}
	],
	"behaviorTypes": [
		{
			"behaviorId": "EightDir",
			"name": "8Direction",
			"sid": 121874764637419
		},
		{
			"behaviorId": "scrollto",
			"name": "ScrollTo",
			"sid": 508421183541406
		}
	],
	"effectTypes": [],
	"animations": {
		"items": [
			{
				"frames": [
					{
						"width": 13,
						"height": 27,
						"originX": 0.5384615384615384,
						"originY": 0.7777777777777778,
						"originalSource": "C:\\Users\\79227\\Desktop\\GGJ-2021-things-to-find.png",
						"exportFormat": "png",
						"exportQuality": 0.8,
						"imageSpriteId": 8661792,
						"useCollisionPoly": true,
						"duration": 1
					},
					{
						"width": 21,
						"height": 25,
						"originX": 0.42857142857142855,
						"originY": 0.84,
						"originalSource": "C:\\Users\\79227\\Desktop\\GGJ-2021-things-to-find.png",
						"exportFormat": "png",
						"exportQuality": 0.8,
						"imageSpriteId": 6149038,
						"useCollisionPoly": true,
						"duration": 1
					},
					{
						"width": 23,
						"height": 22,
						"originX": 0.30434782608695654,
						"originY": 0.5,
						"originalSource": "C:\\Users\\79227\\Desktop\\GGJ-2021-things-to-find.png",
						"exportFormat": "png",
						"exportQuality": 0.8,
						"imageSpriteId": 3985418,
						"useCollisionPoly": true,
						"duration": 1
					},
					{
						"width": 10,
						"height": 15,
						"originX": 0.4,
						"originY": 0.6666666666666666,
						"originalSource": "C:\\Users\\79227\\Desktop\\GGJ-2021-things-to-find.png",
						"exportFormat": "png",
						"exportQuality": 0.8,
						"imageSpriteId": 5847579,
						"useCollisionPoly": true,
						"duration": 1
					},
					{
						"width": 8,
						"height": 14,
						"originX": 0.625,
						"originY": 0.7142857142857143,
						"originalSource": "C:\\Users\\79227\\Desktop\\GGJ-2021-things-to-find.png",
						"exportFormat": "png",
						"exportQuality": 0.8,
						"imageSpriteId": 7348368,
						"useCollisionPoly": true,
						"duration": 1
					},
					{
						"width": 10,
						"height": 9,
						"originX": 0.5,
						"originY": 0.8888888888888888,
						"originalSource": "C:\\Users\\79227\\Desktop\\GGJ-2021-things-to-find.png",
						"exportFormat": "png",
						"exportQuality": 0.8,
						"imageSpriteId": 7444431,
						"useCollisionPoly": true,
						"duration": 1
					},
					{
						"width": 39,
						"height": 10,
						"originX": 0.4358974358974359,
						"originY": 0.8,
						"originalSource": "C:\\Users\\79227\\Desktop\\GGJ-2021-things-to-find.png",
						"exportFormat": "png",
						"exportQuality": 0.8,
						"imageSpriteId": 811759,
						"useCollisionPoly": true,
						"duration": 1
					},
					{
						"width": 12,
						"height": 20,
						"originX": 0.4166666666666667,
						"originY": 0.9,
						"originalSource": "C:\\Users\\79227\\Desktop\\GGJ-2021-things-to-find.png",
						"exportFormat": "png",
						"exportQuality": 0.8,
						"imageSpriteId": 6451466,
						"useCollisionPoly": true,
						"duration": 1
					},
					{
						"width": 13,
						"height": 12,
						"originX": 0.46153846153846156,
						"originY": 0.9166666666666666,
						"originalSource": "C:\\Users\\79227\\Desktop\\GGJ-2021-things-to-find.png",
						"exportFormat": "png",
						"exportQuality": 0.8,
						"imageSpriteId": 6855466,
						"useCollisionPoly": true,
						"duration": 1
					},
					{
						"width": 14,
						"height": 11,
						"originX": 0.5,
						"originY": 0.7272727272727273,
						"originalSource": "C:\\Users\\79227\\Desktop\\GGJ-2021-things-to-find.png",
						"exportFormat": "png",
						"exportQuality": 0.8,
						"imageSpriteId": 5736859,
						"useCollisionPoly": true,
						"duration": 1
					},
					{
						"width": 8,
						"height": 16,
						"originX": 0.5,
						"originY": 0.875,
						"originalSource": "C:\\Users\\79227\\Desktop\\GGJ-2021-things-to-find.png",
						"exportFormat": "png",
						"exportQuality": 0.8,
						"imageSpriteId": 6380251,
						"useCollisionPoly": true,
						"duration": 1
					},
					{
						"width": 38,
						"height": 14,
						"originX": 0.4473684210526316,
						"originY": 0.7142857142857143,
						"originalSource": "C:\\Users\\79227\\Desktop\\GGJ-2021-things-to-find.png",
						"exportFormat": "png",
						"exportQuality": 0.8,
						"imageSpriteId": 3258893,
						"useCollisionPoly": true,
						"duration": 1
					}
				],
				"sid": 421764350873481,
				"name": "Animation 1",
				"isLooping": false,
				"isPingPong": false,
				"repeatCount": 1,
				"repeatTo": 0,
				"speed": 0
			}
		],
		"subfolders": []
	}
}